README.rst
moscow_yandex_transport.py
setup.cfg
setup.py
moscow_yandex_transport.egg-info/PKG-INFO
moscow_yandex_transport.egg-info/SOURCES.txt
moscow_yandex_transport.egg-info/dependency_links.txt
moscow_yandex_transport.egg-info/requires.txt
moscow_yandex_transport.egg-info/top_level.txt